storagelayer/__init__.py
storagelayer/archive.py
storagelayer/file.py
storagelayer/gs.py
storagelayer/s3.py
storagelayer/util.py
storagelayer/virtual.py
storagelayer-0.5.2.dist-info/DESCRIPTION.rst
storagelayer-0.5.2.dist-info/METADATA
storagelayer-0.5.2.dist-info/RECORD
storagelayer-0.5.2.dist-info/WHEEL
storagelayer-0.5.2.dist-info/metadata.json
storagelayer-0.5.2.dist-info/namespace_packages.txt
storagelayer-0.5.2.dist-info/top_level.txt
storagelayer-0.5.2.dist-info/zip-safe
tests/__init__.py
tests/test_file.py
tests/test_s3.py
