Metadata-Version: 2.0
Name: storagelayer
Version: 0.5.2
Summary: Content-addressable storage for aleph and memorious
Home-page: http://github.com/alephdata/storagelayer
Author: Friedrich Lindenberg
Author-email: friedrich@pudo.org
License: MIT
Keywords: storage files s3
Platform: UNKNOWN
Classifier: Development Status :: 3 - Alpha
Classifier: Intended Audience :: Developers
Classifier: License :: OSI Approved :: MIT License
Classifier: Operating System :: OS Independent
Classifier: Programming Language :: Python :: 3.4
Classifier: Programming Language :: Python :: 3.5
Classifier: Programming Language :: Python :: 3.6
Requires-Dist: cryptography (>=2.3.1)
Requires-Dist: boto3 (>=1.4.6)
Requires-Dist: google-cloud-storage (>=1.10.0)
Requires-Dist: normality (>=0.6.1)
